renfield/__init__.py
renfield/__main__.py
renfield/lib/__init__.py
renfield/lib/database.py
renfield/lib/fsutils.py
renfield/lib/ham_utility.py
renfield/lib/plugin_common.py
renfield/lib/version.py
renfield/lib/versiontest.py
renfield/plugins/10_10_fall_cw.py
renfield/plugins/10_10_spring_cw.py
renfield/plugins/10_10_summer_phone.py
renfield/plugins/10_10_winter_phone.py
renfield/plugins/__init__.py
renfield/plugins/ari_40_80.py
renfield/plugins/arrl_10m.py
renfield/plugins/arrl_160m.py
renfield/plugins/arrl_dx_cw.py
renfield/plugins/arrl_dx_ssb.py
renfield/plugins/arrl_field_day.py
renfield/plugins/arrl_rtty_ru.py
renfield/plugins/arrl_ss_cw.py
renfield/plugins/arrl_ss_phone.py
renfield/plugins/arrl_vhf_jan.py
renfield/plugins/arrl_vhf_jun.py
renfield/plugins/arrl_vhf_sep.py
renfield/plugins/canada_day.py
renfield/plugins/cq_160_cw.py
renfield/plugins/cq_160_ssb.py
renfield/plugins/cq_wpx_cw.py
renfield/plugins/cq_wpx_rtty.py
renfield/plugins/cq_wpx_ssb.py
renfield/plugins/cq_ww_cw.py
renfield/plugins/cq_ww_rtty.py
renfield/plugins/cq_ww_ssb.py
renfield/plugins/cwo.py
renfield/plugins/cwt.py
renfield/plugins/darc_vhf.py
renfield/plugins/darc_xmas.py
renfield/plugins/ea_majistad_cw.py
renfield/plugins/ea_majistad_ssb.py
renfield/plugins/ea_rtty.py
renfield/plugins/es_open.py
renfield/plugins/general_logging.py
renfield/plugins/helvetia.py
renfield/plugins/iaru_fieldday_r1_cw.py
renfield/plugins/iaru_fieldday_r1_ssb.py
renfield/plugins/iaru_hf.py
renfield/plugins/icwc_mst.py
renfield/plugins/jidx_cw.py
renfield/plugins/jidx_ph.py
renfield/plugins/k1usn_sst.py
renfield/plugins/labre_rs_digi.py
renfield/plugins/lz-dx.py
renfield/plugins/naqp_cw.py
renfield/plugins/naqp_rtty.py
renfield/plugins/naqp_ssb.py
renfield/plugins/phone_weekly_test.py
renfield/plugins/raem.py
renfield/plugins/randomgram.py
renfield/plugins/ref_cw.py
renfield/plugins/ref_ssb.py
renfield/plugins/sac_cw.py
renfield/plugins/sac_ssb.py
renfield/plugins/spdx.py
renfield/plugins/stew_perry_topband.py
renfield-25.12.21.dist-info/licenses/LICENSE
renfield-25.12.21.dist-info/METADATA
renfield-25.12.21.dist-info/WHEEL
renfield-25.12.21.dist-info/entry_points.txt
renfield-25.12.21.dist-info/top_level.txt
renfield-25.12.21.dist-info/RECORD
