Metadata-Version: 2.4
Name: renfield
Version: 25.12.21
Summary: Hapless and flawed servant of the not1mm contest logger.
Author-email: Michael Bridak <michael.bridak@gmail.com>
Project-URL: Homepage, https://github.com/mbridak/renfield
Project-URL: Bug Tracker, https://github.com/mbridak/renfield/issues
Requires-Python: >=3.11
License-File: LICENSE
Requires-Dist: appdata>=2.2.1
Requires-Dist: dicttoxml>=1.7.16
Requires-Dist: rich>=14.1.0
Requires-Dist: textual>=6.2.0
Dynamic: license-file
